{
    "doc-pro-ai-id": "f2d8ef88-1137-474a-a23f-09bd5389cfdd",
    "status": "success",
    "error_code": "",
    "details": "Request processed successfully.",
    "processing_time": {
        "start_time": 1748256045.9977343,
        "end_time": 1748256054.3245559,
        "total_time_taken": 8.326821565628052
    },
    "results": {
        "financialDocuments": [
            {
                "summary": {
                    "expectedFieldCount": 3,
                    "extractedFieldCount": 3,
                    "status": "success"
                },
                "keyValues": {
                    "totalRevenue": {
                        "value": "298,412",
                        "status": "success",
                        "reason": ""
                    },
                    "totalExpense": {
                        "value": "267,394",
                        "status": "success",
                        "reason": ""
                    },
                    "netOperatingIncome": {
                        "value": "31,018",
                        "status": "success",
                        "reason": ""
                    }
                }
            }
        ]
    }
}